CHANGELOG.md
LICENSE
MANIFEST.in
README.md
requirements.txt
requirements_dev.txt
setup.cfg
setup.py
landsat_cogeo_mosaic/__init__.py
landsat_cogeo_mosaic/cli.py
landsat_cogeo_mosaic/constants.py
landsat_cogeo_mosaic/db.py
landsat_cogeo_mosaic/grid.py
landsat_cogeo_mosaic/index.py
landsat_cogeo_mosaic/mosaic.py
landsat_cogeo_mosaic/stac.py
landsat_cogeo_mosaic/util.py
landsat_cogeo_mosaic/validate.py
landsat_cogeo_mosaic/visualize.py
landsat_cogeo_mosaic.egg-info/PKG-INFO
landsat_cogeo_mosaic.egg-info/SOURCES.txt
landsat_cogeo_mosaic.egg-info/dependency_links.txt
landsat_cogeo_mosaic.egg-info/entry_points.txt
landsat_cogeo_mosaic.egg-info/not-zip-safe
landsat_cogeo_mosaic.egg-info/requires.txt
landsat_cogeo_mosaic.egg-info/top_level.txt
landsat_cogeo_mosaic/data/pr_index.json.gz